.svnignore
CHANGES.txt
CONTRIBUTORS.txt
README.txt
setup.cfg
setup.py
docs/INSTALL.txt
docs/LICENSE.GPL
docs/LICENSE.txt
slc/__init__.py
slc.clicksearch.egg-info/PKG-INFO
slc.clicksearch.egg-info/SOURCES.txt
slc.clicksearch.egg-info/dependency_links.txt
slc.clicksearch.egg-info/entry_points.txt
slc.clicksearch.egg-info/namespace_packages.txt
slc.clicksearch.egg-info/not-zip-safe
slc.clicksearch.egg-info/requires.txt
slc.clicksearch.egg-info/top_level.txt
slc/clicksearch/README.txt
slc/clicksearch/TODO.txt
slc/clicksearch/__init__.py
slc/clicksearch/config.py
slc/clicksearch/configure.zcml
slc/clicksearch/interfaces.py
slc/clicksearch/setuphandlers.py
slc/clicksearch/tests.py
slc/clicksearch/util.py
slc/clicksearch/version.txt
slc/clicksearch/vocabulary.py
slc/clicksearch/Extensions/addTestContent.py
slc/clicksearch/browser/__init__.py
slc/clicksearch/browser/clicksearch.css
slc/clicksearch/browser/clicksearch.py
slc/clicksearch/browser/config.py
slc/clicksearch/browser/configure.zcml
slc/clicksearch/browser/indexes.py
slc/clicksearch/browser/results.py
slc/clicksearch/browser/widgets.py
slc/clicksearch/browser/images/clicksearch_results_bar.gif
slc/clicksearch/browser/templates/atvm_tree_index.pt
slc/clicksearch/browser/templates/clicksearch.pt
slc/clicksearch/browser/templates/default_index.pt
slc/clicksearch/browser/templates/details.pt
slc/clicksearch/browser/templates/simple_result.pt
slc/clicksearch/browser/templates/video_result.pt
slc/clicksearch/browser/widgets/dropdown.pt
slc/clicksearch/browser/widgets/simple_list.pt
slc/clicksearch/browser/widgets/simple_list_selected.pt
slc/clicksearch/browser/widgets/subject.pt
slc/clicksearch/browser/widgets/tree_list.pt
slc/clicksearch/browser/widgets/tree_list_selected.pt
slc/clicksearch/portlets/__init__.py
slc/clicksearch/portlets/clicksearch_box.pt
slc/clicksearch/portlets/clicksearch_box.py
slc/clicksearch/portlets/configure.zcml
slc/clicksearch/profiles/default/actionicons.xml
slc/clicksearch/profiles/default/browserlayer.xml
slc/clicksearch/profiles/default/componentregistry.xml
slc/clicksearch/profiles/default/controlpanel.xml
slc/clicksearch/profiles/default/cssregistry.xml
slc/clicksearch/profiles/default/import_steps.xml
slc/clicksearch/profiles/default/metadata.xml
slc/clicksearch/profiles/default/portlets.xml
