Metadata-Version: 1.0
Name: slc.clicksearch
Version: 1.4.4
Summary: A portlet that allows searching by metadata
Home-page: https://svn.syslab.com/svn/syslabcom/clicksearch/
Author: Syslab.com GmbH
Author-email: info@syslab.com
License: GPL
Keywords: portlet search browse
Platform: UNKNOWN
Classifier: Framework :: Plone
Classifier: Framework :: Zope2
Classifier: Framework :: Zope3
Classifier: Programming Language :: Python
Classifier: Topic :: Software Development :: Libraries :: Python Modules
